README.rst
setup.py
lib/BaseTransmitter.py
lib/NATSTransmitter.py
lib/Transmitter.py
lib/__init__.py
pythonEventB.egg-info/PKG-INFO
pythonEventB.egg-info/SOURCES.txt
pythonEventB.egg-info/dependency_links.txt
pythonEventB.egg-info/requires.txt
pythonEventB.egg-info/top_level.txt