Metadata-Version: 1.1
Name: pythonEventB
Version: 1.0.5
Summary: A simple client for events in python
Home-page: https://gitlab.com/cuemby/ecorp/python-event-bridge
Author: Cuemby S.A.
Author-email: UNKNOWN
License: UNKNOWN
Platform: UNKNOWN
Classifier: Development Status :: 3 - Alpha
Classifier: Intended Audience :: Developers
Classifier: Topic :: Software Development :: Build Tools
Classifier: License :: OSI Approved :: MIT License
Classifier: Programming Language :: Python :: 3.5
Classifier: Programming Language :: Python :: 3.6
